django_tenants_celery_beat/__init__.py
django_tenants_celery_beat/admin.py
django_tenants_celery_beat/apps.py
django_tenants_celery_beat/models.py
django_tenants_celery_beat/utils.py
django_tenants_celery_beat/migrations/__init__.py
django_tenants_celery_beat-0.2.1.dist-info/LICENSE
django_tenants_celery_beat-0.2.1.dist-info/METADATA
django_tenants_celery_beat-0.2.1.dist-info/WHEEL
django_tenants_celery_beat-0.2.1.dist-info/top_level.txt
django_tenants_celery_beat-0.2.1.dist-info/RECORD
