Metadata-Version: 2.1
Name: django-tenants-celery-beat
Version: 0.2.1
Summary: Support for celery beat in multitenant Django projects
Home-page: https://github.com/QuickRelease/django-tenants-celery-beat
Author: David Vaughan
Author-email: david.vaughan@quickrelease.co.uk
Maintainer: Quick Release (Automotive) Ltd.
License: MIT
Keywords: django tenants celery beat multitenancy postgres postgresql
Classifier: Programming Language :: Python :: 3
Classifier: Framework :: Django :: 2.0
Classifier: Framework :: Django :: 2.1
Classifier: Framework :: Django :: 2.2
Classifier: Framework :: Django :: 3.0
Classifier: Framework :: Django :: 3.1
Classifier: Framework :: Django :: 3.2
Classifier: License :: OSI Approved :: MIT License
Classifier: Intended Audience :: Developers
Classifier: Operating System :: OS Independent
License-File: LICENSE
